{
  "kind": "collectionType",
  "collectionName": "debuts",
  "info": {
    "singularName": "debut",
    "pluralName": "debuts",
    "displayName": "Debut"
  },
  "options": {
    "draftAndPublish": true
  },
  "pluginOptions": {
    "i18n": {
      "localized": true
    }
  },
  "attributes": {
    "title": {
      "type": "string",
      "pluginOptions": {
        "i18n": {
          "localized": true
        }
      }
    },
    "content": {
      "type": "richtext",
      "pluginOptions": {
        "i18n": {
          "localized": true
        }
      }
    }
  }
}
